MANIFEST.in
README.rst
setup.cfg
setup.py
wladmin/__init__.py
wladmin.egg-info/PKG-INFO
wladmin.egg-info/SOURCES.txt
wladmin.egg-info/dependency_links.txt
wladmin.egg-info/not-zip-safe
wladmin.egg-info/top_level.txt
wladmin/static/admin/js/actions.js
wladmin/static/admin/js/actions.min.js
wladmin/static/wladmin/css/base.css
wladmin/static/wladmin/css/changelist.css
wladmin/static/wladmin/css/dashboard.css
wladmin/static/wladmin/css/documentation.css
wladmin/static/wladmin/css/forms.css
wladmin/static/wladmin/css/login.css
wladmin/static/wladmin/css/modules.css
wladmin/static/wladmin/css/reset.css
wladmin/static/wladmin/css/rtl.css
wladmin/static/wladmin/css/tables.css
wladmin/static/wladmin/css/typography.css
wladmin/static/wladmin/css/webkit-gradients.css
wladmin/static/wladmin/css/widgets.css
wladmin/static/wladmin/img/icon_calendar.gif
wladmin/static/wladmin/img/icon_clock.gif
wladmin/static/wladmin/img/wladmin-icon.png
wladmin/static/wladmin/img/admin/arrow-down.gif
wladmin/static/wladmin/img/admin/arrow-up.gif
wladmin/static/wladmin/img/admin/changelist-bg.gif
wladmin/static/wladmin/img/admin/changelist-bg_rtl.gif
wladmin/static/wladmin/img/admin/chooser-bg.gif
wladmin/static/wladmin/img/admin/chooser_stacked-bg.gif
wladmin/static/wladmin/img/admin/default-bg-reverse.gif
wladmin/static/wladmin/img/admin/default-bg.gif
wladmin/static/wladmin/img/admin/deleted-overlay.gif
wladmin/static/wladmin/img/admin/icon-no.gif
wladmin/static/wladmin/img/admin/icon-unknown.gif
wladmin/static/wladmin/img/admin/icon-yes.gif
wladmin/static/wladmin/img/admin/icon_addlink.gif
wladmin/static/wladmin/img/admin/icon_alert.gif
wladmin/static/wladmin/img/admin/icon_calendar.gif
wladmin/static/wladmin/img/admin/icon_changelink.gif
wladmin/static/wladmin/img/admin/icon_clock.gif
wladmin/static/wladmin/img/admin/icon_deletelink.gif
wladmin/static/wladmin/img/admin/icon_error.gif
wladmin/static/wladmin/img/admin/icon_searchbox.png
wladmin/static/wladmin/img/admin/icon_success.gif
wladmin/static/wladmin/img/admin/inline-delete-8bit.png
wladmin/static/wladmin/img/admin/inline-delete.png
