Metadata-Version: 1.0
Name: wladmin
Version: 1.6
Summary: wladmin skin for the WenlinCMS.
Home-page: http://wenlincms.com
Author: Feichi LONG
Author-email: feichi@longfeichi.com
License: UNKNOWN
Platform: UNKNOWN
